LICENSE
README.md
setup.py
charset_mnbvc/__init__.py
charset_mnbvc/api.py
charset_mnbvc/common_utils.py
charset_mnbvc/constant.py
charset_mnbvc/verify.py
charset_mnbvc/version.py
charset_mnbvc.egg-info/PKG-INFO
charset_mnbvc.egg-info/SOURCES.txt
charset_mnbvc.egg-info/dependency_links.txt
charset_mnbvc.egg-info/requires.txt
charset_mnbvc.egg-info/top_level.txt