Metadata-Version: 2.1
Name: charset-mnbvc
Version: 0.0.16
Summary: 本项目旨在对大量文本文件进行快速编码检测以辅助mnbvc语料集项目的数据清洗工作
Home-page: https://github.com/alanshi/charset_mnbvc
Author: Alan Shi
Author-email: alan.shi86@gmail.com
License: UNKNOWN
Project-URL: Bug Reports, https://github.com/alanshi/charset_mnbvc/issues
Project-URL: Source, https://github.com/alanshi/charset_mnbvc/
Platform: UNKNOWN
Classifier: License :: OSI Approved :: MIT License
Classifier: Programming Language :: Python :: 3
Requires-Python: >=3.7
License-File: LICENSE
